star_doc_map/__init__.py
star_doc_map-0.0.1.dev0.dist-info/DESCRIPTION.rst
star_doc_map-0.0.1.dev0.dist-info/METADATA
star_doc_map-0.0.1.dev0.dist-info/RECORD
star_doc_map-0.0.1.dev0.dist-info/WHEEL
star_doc_map-0.0.1.dev0.dist-info/entry_points.txt
star_doc_map-0.0.1.dev0.dist-info/metadata.json
star_doc_map-0.0.1.dev0.dist-info/top_level.txt
